{
  "$schema": "https://developer.microsoft.com/json-schemas/fabric/item/report/definition/visualContainer/2.1.0/schema.json",
  "name": "e1a003b6585aa757a5cd",
  "position": {
    "x": 85.371525384314992,
    "y": 66.573813391170987,
    "z": 0,
    "height": 494.23631123919313,
    "width": 654.17867435158507,
    "tabOrder": 1000
  },
  "visual": {
    "visualType": "pieChart",
    "query": {
      "queryState": {
        "Category": {
          "projections": [
            {
              "field": {
                "Column": {
                  "Expression": {
                    "SourceRef": {
                      "Entity": "Armenia Import"
                    }
                  },
                  "Property": "SUPPLIER_NAME_EN"
                }
              },
              "queryRef": "Armenia Import.SUPPLIER_NAME_EN",
              "nativeQueryRef": "SUPPLIER_NAME_EN",
              "active": true
            }
          ]
        },
        "Y": {
          "projections": [
            {
              "field": {
                "Measure": {
                  "Expression": {
                    "SourceRef": {
                      "Entity": "All Measures"
                    }
                  },
                  "Property": "Total Value"
                }
              },
              "queryRef": "All Measures.Total Value",
              "nativeQueryRef": "Value",
              "displayName": "Value"
            }
          ],
          "fieldParameters": [
            {
              "parameterExpr": {
                "Column": {
                  "Expression": {
                    "SourceRef": {
                      "Entity": "Data"
                    }
                  },
                  "Property": "Data"
                }
              },
              "index": 0,
              "length": 1
            }
          ]
        }
      },
      "sortDefinition": {
        "sort": [
          {
            "field": {
              "Measure": {
                "Expression": {
                  "SourceRef": {
                    "Entity": "All Measures"
                  }
                },
                "Property": "Total Value"
              }
            },
            "direction": "Descending"
          }
        ],
        "isDefaultSort": true
      }
    },
    "objects": {
      "legend": [
        {
          "properties": {
            "show": {
              "expr": {
                "Literal": {
                  "Value": "false"
                }
              }
            },
            "fontFamily": {
              "expr": {
                "Literal": {
                  "Value": "'Arial'"
                }
              }
            },
            "labelColor": {
              "solid": {
                "color": {
                  "expr": {
                    "ThemeDataColor": {
                      "ColorId": 1,
                      "Percent": 0
                    }
                  }
                }
              }
            },
            "fontSize": {
              "expr": {
                "Literal": {
                  "Value": "9D"
                }
              }
            }
          }
        }
      ],
      "dataPoint": [
        {
          "properties": {
            "fill": {
              "solid": {
                "color": {
                  "expr": {
                    "Literal": {
                      "Value": "'#8EF9F3'"
                    }
                  }
                }
              }
            }
          },
          "selector": {
            "data": [
              {
                "scopeId": {
                  "Comparison": {
                    "ComparisonKind": 0,
                    "Left": {
                      "Column": {
                        "Expression": {
                          "SourceRef": {
                            "Entity": "Armenia Import"
                          }
                        },
                        "Property": "UNIT"
                      }
                    },
                    "Right": {
                      "Literal": {
                        "Value": "'NOS'"
                      }
                    }
                  }
                }
              }
            ]
          }
        },
        {
          "properties": {
            "fill": {
              "solid": {
                "color": {
                  "expr": {
                    "Literal": {
                      "Value": "'#82E832'"
                    }
                  }
                }
              }
            }
          },
          "selector": {
            "data": [
              {
                "scopeId": {
                  "Comparison": {
                    "ComparisonKind": 0,
                    "Left": {
                      "Column": {
                        "Expression": {
                          "SourceRef": {
                            "Entity": "Armenia Import"
                          }
                        },
                        "Property": "UNIT"
                      }
                    },
                    "Right": {
                      "Literal": {
                        "Value": "'PCS'"
                      }
                    }
                  }
                }
              }
            ]
          }
        },
        {
          "properties": {
            "fill": {
              "solid": {
                "color": {
                  "expr": {
                    "Literal": {
                      "Value": "'#EF3054'"
                    }
                  }
                }
              }
            }
          },
          "selector": {
            "data": [
              {
                "scopeId": {
                  "Comparison": {
                    "ComparisonKind": 0,
                    "Left": {
                      "Column": {
                        "Expression": {
                          "SourceRef": {
                            "Entity": "Armenia Import"
                          }
                        },
                        "Property": "UNIT"
                      }
                    },
                    "Right": {
                      "Literal": {
                        "Value": "'MTS'"
                      }
                    }
                  }
                }
              }
            ]
          }
        },
        {
          "properties": {
            "fill": {
              "solid": {
                "color": {
                  "expr": {
                    "Literal": {
                      "Value": "'#0081A7'"
                    }
                  }
                }
              }
            }
          },
          "selector": {
            "data": [
              {
                "scopeId": {
                  "Comparison": {
                    "ComparisonKind": 0,
                    "Left": {
                      "Column": {
                        "Expression": {
                          "SourceRef": {
                            "Entity": "Armenia Import"
                          }
                        },
                        "Property": "SUPPLIER_NAME"
                      }
                    },
                    "Right": {
                      "Literal": {
                        "Value": "'SIG COMBIBLOC LIMITED'"
                      }
                    }
                  }
                }
              }
            ]
          }
        },
        {
          "properties": {
            "fill": {
              "solid": {
                "color": {
                  "expr": {
                    "Literal": {
                      "Value": "'#FF595E'"
                    }
                  }
                }
              }
            }
          },
          "selector": {
            "data": [
              {
                "scopeId": {
                  "Comparison": {
                    "ComparisonKind": 0,
                    "Left": {
                      "Column": {
                        "Expression": {
                          "SourceRef": {
                            "Entity": "Armenia Import"
                          }
                        },
                        "Property": "SUPPLIER_NAME"
                      }
                    },
                    "Right": {
                      "Literal": {
                        "Value": "'SIG COMBIBLOC LTD'"
                      }
                    }
                  }
                }
              }
            ]
          }
        },
        {
          "properties": {
            "fill": {
              "solid": {
                "color": {
                  "expr": {
                    "Literal": {
                      "Value": "'#FF9E00'"
                    }
                  }
                }
              }
            }
          },
          "selector": {
            "data": [
              {
                "scopeId": {
                  "Comparison": {
                    "ComparisonKind": 0,
                    "Left": {
                      "Column": {
                        "Expression": {
                          "SourceRef": {
                            "Entity": "Armenia Import"
                          }
                        },
                        "Property": "SUPPLIER_NAME"
                      }
                    },
                    "Right": {
                      "Literal": {
                        "Value": "'SUNWODA ELECTRONIC CO LIMITED'"
                      }
                    }
                  }
                }
              }
            ]
          }
        }
      ],
      "labels": [
        {
          "properties": {
            "labelStyle": {
              "expr": {
                "Literal": {
                  "Value": "'Category, data value, percent of total'"
                }
              }
            },
            "fontFamily": {
              "expr": {
                "Literal": {
                  "Value": "'Arial'"
                }
              }
            },
            "fontSize": {
              "expr": {
                "Literal": {
                  "Value": "9D"
                }
              }
            },
            "bold": {
              "expr": {
                "Literal": {
                  "Value": "false"
                }
              }
            }
          }
        },
        {
          "properties": {
            "color": {
              "solid": {
                "color": {
                  "expr": {
                    "ThemeDataColor": {
                      "ColorId": 1,
                      "Percent": 0
                    }
                  }
                }
              }
            }
          },
          "selector": {
            "data": [
              {
                "dataViewWildcard": {
                  "matchingOption": 1
                }
              }
            ]
          }
        }
      ]
    },
    "visualContainerObjects": {
      "title": [
        {
          "properties": {
            "text": {
              "expr": {
                "Measure": {
                  "Expression": {
                    "SourceRef": {
                      "Entity": "TopN Supplier"
                    }
                  },
                  "Property": "Title Supplier"
                }
              }
            },
            "show": {
              "expr": {
                "Literal": {
                  "Value": "true"
                }
              }
            },
            "titleWrap": {
              "expr": {
                "Literal": {
                  "Value": "true"
                }
              }
            },
            "fontFamily": {
              "expr": {
                "Literal": {
                  "Value": "'Arial'"
                }
              }
            },
            "bold": {
              "expr": {
                "Literal": {
                  "Value": "true"
                }
              }
            }
          }
        }
      ],
      "background": [
        {
          "properties": {
            "show": {
              "expr": {
                "Literal": {
                  "Value": "true"
                }
              }
            },
            "transparency": {
              "expr": {
                "Literal": {
                  "Value": "66D"
                }
              }
            },
            "color": {
              "solid": {
                "color": {
                  "expr": {
                    "Literal": {
                      "Value": "'#F6FAFF'"
                    }
                  }
                }
              }
            }
          }
        }
      ],
      "dropShadow": [
        {
          "properties": {
            "show": {
              "expr": {
                "Literal": {
                  "Value": "true"
                }
              }
            },
            "color": {
              "solid": {
                "color": {
                  "expr": {
                    "Literal": {
                      "Value": "'#b3b3b3'"
                    }
                  }
                }
              }
            }
          }
        }
      ]
    },
    "drillFilterOtherVisuals": true
  },
  "parentGroupName": "2bbb7298d079a42e845c",
  "filterConfig": {
    "filters": [
      {
        "name": "0baca9fb40498a33ca4c",
        "field": {
          "Measure": {
            "Expression": {
              "SourceRef": {
                "Entity": "TopN Supplier"
              }
            },
            "Property": "TOPN Supplier Rank"
          }
        },
        "type": "Advanced",
        "filter": {
          "Version": 2,
          "From": [
            {
              "Name": "t",
              "Entity": "TopN Supplier",
              "Type": 0
            }
          ],
          "Where": [
            {
              "Condition": {
                "Comparison": {
                  "ComparisonKind": 0,
                  "Left": {
                    "Measure": {
                      "Expression": {
                        "SourceRef": {
                          "Source": "t"
                        }
                      },
                      "Property": "TOPN Supplier Rank"
                    }
                  },
                  "Right": {
                    "Literal": {
                      "Value": "1L"
                    }
                  }
                }
              }
            }
          ]
        },
        "howCreated": "User"
      }
    ]
  }
}