{
  "$schema": "https://developer.microsoft.com/json-schemas/fabric/item/report/definition/bookmark/1.4.0/schema.json",
  "displayName": "Top 50 Importer",
  "name": "Bookmark7d0f19e800199ba03d6c",
  "options": {
    "applyOnlyToTargetVisuals": true,
    "targetVisualNames": [
      "6b9de63f0e440fe98b75",
      "9a3eeb39951dc5058ac0",
      "15cb0a632b96096e136d"
    ]
  },
  "explorationState": {
    "version": "1.11",
    "activeSection": "ReportSectionee67a0b55c8d901795c9",
    "sections": {
      "ReportSectionee67a0b55c8d901795c9": {
        "visualContainers": {
          "943d5b7b4a00e6015db0": {
            "singleVisual": {
              "visualType": "shape",
              "objects": {}
            }
          },
          "3e595f91e7280a4c0306": {
            "singleVisual": {
              "visualType": "shape",
              "objects": {}
            }
          },
          "f0bfedf23241170c03e0": {
            "singleVisual": {
              "visualType": "shape",
              "objects": {}
            }
          },
          "edfaf55675ab9479da0d": {
            "filters": {
              "byExpr": [
                {
                  "name": "32a2991eb837bf4e9eaf",
                  "type": "Advanced",
                  "expression": {
                    "Aggregation": {
                      "Expression": {
                        "Column": {
                          "Expression": {
                            "SourceRef": {
                              "Entity": "Armenia Import"
                            }
                          },
                          "Property": "RECORDS_TAG"
                        }
                      },
                      "Function": 5
                    }
                  },
                  "howCreated": 0
                }
              ]
            },
            "singleVisual": {
              "visualType": "cardVisual",
              "objects": {},
              "orderBy": [
                {
                  "Direction": 2,
                  "Expression": {
                    "Aggregation": {
                      "Expression": {
                        "Column": {
                          "Expression": {
                            "SourceRef": {
                              "Entity": "Armenia Import"
                            }
                          },
                          "Property": "RECORDS_TAG"
                        }
                      },
                      "Function": 5
                    }
                  }
                }
              ]
            }
          },
          "56cbf2db87a12c4a526c": {
            "filters": {
              "byExpr": [
                {
                  "name": "ff1056b7400a52b8c779",
                  "type": "Advanced",
                  "expression": {
                    "Aggregation": {
                      "Expression": {
                        "Column": {
                          "Expression": {
                            "SourceRef": {
                              "Entity": "Armenia Import"
                            }
                          },
                          "Property": "TOTAL_ASSESS_USD"
                        }
                      },
                      "Function": 0
                    }
                  },
                  "howCreated": 0
                }
              ]
            },
            "singleVisual": {
              "visualType": "cardVisual",
              "objects": {},
              "orderBy": [
                {
                  "Direction": 2,
                  "Expression": {
                    "Aggregation": {
                      "Expression": {
                        "Column": {
                          "Expression": {
                            "SourceRef": {
                              "Entity": "Armenia Import"
                            }
                          },
                          "Property": "TOTAL_ASSESS_USD"
                        }
                      },
                      "Function": 0
                    }
                  }
                }
              ]
            }
          },
          "8e54cfc434762e0c5047": {
            "filters": {
              "byExpr": [
                {
                  "name": "394ad569fdf73e0d482e",
                  "type": "Advanced",
                  "expression": {
                    "Aggregation": {
                      "Expression": {
                        "Column": {
                          "Expression": {
                            "SourceRef": {
                              "Entity": "Armenia Import"
                            }
                          },
                          "Property": "STD_QUANTITY"
                        }
                      },
                      "Function": 0
                    }
                  },
                  "howCreated": 0
                }
              ]
            },
            "singleVisual": {
              "visualType": "cardVisual",
              "objects": {},
              "orderBy": [
                {
                  "Direction": 2,
                  "Expression": {
                    "Aggregation": {
                      "Expression": {
                        "Column": {
                          "Expression": {
                            "SourceRef": {
                              "Entity": "Armenia Import"
                            }
                          },
                          "Property": "QUANTITY"
                        }
                      },
                      "Function": 0
                    }
                  }
                }
              ]
            }
          },
          "e7c3000a6b328c17c0db": {
            "filters": {
              "byExpr": [
                {
                  "name": "cc1a109cdd5b28fde23d",
                  "type": "Advanced",
                  "expression": {
                    "Aggregation": {
                      "Expression": {
                        "Column": {
                          "Expression": {
                            "SourceRef": {
                              "Entity": "Armenia Import"
                            }
                          },
                          "Property": "HS_CODE"
                        }
                      },
                      "Function": 2
                    }
                  },
                  "howCreated": 0
                }
              ]
            },
            "singleVisual": {
              "visualType": "cardVisual",
              "objects": {},
              "orderBy": [
                {
                  "Direction": 2,
                  "Expression": {
                    "Aggregation": {
                      "Expression": {
                        "Column": {
                          "Expression": {
                            "SourceRef": {
                              "Entity": "Armenia Import"
                            }
                          },
                          "Property": "HS_CODE"
                        }
                      },
                      "Function": 2
                    }
                  }
                }
              ]
            }
          },
          "cda34c4088ba0827dc88": {
            "filters": {
              "byExpr": [
                {
                  "name": "ef6874fdf1669e4221e6",
                  "type": "Advanced",
                  "expression": {
                    "Aggregation": {
                      "Expression": {
                        "Column": {
                          "Expression": {
                            "SourceRef": {
                              "Entity": "Armenia Import"
                            }
                          },
                          "Property": "IMPORTER_NAME"
                        }
                      },
                      "Function": 2
                    }
                  },
                  "howCreated": 0
                }
              ]
            },
            "singleVisual": {
              "visualType": "cardVisual",
              "objects": {},
              "orderBy": [
                {
                  "Direction": 2,
                  "Expression": {
                    "Aggregation": {
                      "Expression": {
                        "Column": {
                          "Expression": {
                            "SourceRef": {
                              "Entity": "Armenia Import"
                            }
                          },
                          "Property": "IMPORTER_NAME"
                        }
                      },
                      "Function": 2
                    }
                  }
                }
              ]
            }
          },
          "24dbe1b066b08e7a6ae2": {
            "filters": {
              "byExpr": [
                {
                  "name": "9a9713347fd2d70de863",
                  "type": "Advanced",
                  "expression": {
                    "Aggregation": {
                      "Expression": {
                        "Column": {
                          "Expression": {
                            "SourceRef": {
                              "Entity": "Armenia Import"
                            }
                          },
                          "Property": "SUPPLIER_NAME"
                        }
                      },
                      "Function": 2
                    }
                  },
                  "howCreated": 0
                }
              ]
            },
            "singleVisual": {
              "visualType": "cardVisual",
              "objects": {},
              "orderBy": [
                {
                  "Direction": 2,
                  "Expression": {
                    "Aggregation": {
                      "Expression": {
                        "Column": {
                          "Expression": {
                            "SourceRef": {
                              "Entity": "Armenia Import"
                            }
                          },
                          "Property": "SUPPLIER_NAME"
                        }
                      },
                      "Function": 2
                    }
                  }
                }
              ]
            }
          },
          "4d5e90da35a4678a33cc": {
            "filters": {
              "byExpr": [
                {
                  "name": "2a47a73bae3c8227fef6",
                  "type": "Categorical",
                  "expression": {
                    "Column": {
                      "Expression": {
                        "SourceRef": {
                          "Entity": "Armenia Import"
                        }
                      },
                      "Property": "IMPORTER_NAME"
                    }
                  },
                  "howCreated": 0
                },
                {
                  "name": "b9d15fca54019aa841a3",
                  "type": "Categorical",
                  "expression": {
                    "Column": {
                      "Expression": {
                        "SourceRef": {
                          "Entity": "Armenia Import"
                        }
                      },
                      "Property": "HS_CODE"
                    }
                  },
                  "howCreated": 0
                },
                {
                  "name": "8e7f29c1d7919ad0243e",
                  "type": "Advanced",
                  "expression": {
                    "Aggregation": {
                      "Expression": {
                        "Column": {
                          "Expression": {
                            "SourceRef": {
                              "Entity": "Armenia Import"
                            }
                          },
                          "Property": "TOTAL_ASSESS_USD"
                        }
                      },
                      "Function": 0
                    }
                  },
                  "howCreated": 0
                },
                {
                  "name": "4f5ff7adc3e35ab2cd31",
                  "type": "Advanced",
                  "expression": {
                    "Arithmetic": {
                      "Left": {
                        "Aggregation": {
                          "Expression": {
                            "Column": {
                              "Expression": {
                                "SourceRef": {
                                  "Entity": "Armenia Import"
                                }
                              },
                              "Property": "TOTAL_ASSESS_USD"
                            }
                          },
                          "Function": 0
                        }
                      },
                      "Right": {
                        "ScopedEval": {
                          "Expression": {
                            "Aggregation": {
                              "Expression": {
                                "Column": {
                                  "Expression": {
                                    "SourceRef": {
                                      "Entity": "Armenia Import"
                                    }
                                  },
                                  "Property": "TOTAL_ASSESS_USD"
                                }
                              },
                              "Function": 0
                            }
                          },
                          "Scope": []
                        }
                      },
                      "Operator": 3
                    }
                  },
                  "howCreated": 0
                },
                {
                  "name": "12a2d514a4b82cc18c6c",
                  "type": "Advanced",
                  "expression": {
                    "Aggregation": {
                      "Expression": {
                        "Column": {
                          "Expression": {
                            "SourceRef": {
                              "Entity": "Armenia Import"
                            }
                          },
                          "Property": "STD_QUANTITY"
                        }
                      },
                      "Function": 0
                    }
                  },
                  "howCreated": 0
                }
              ]
            },
            "singleVisual": {
              "visualType": "EximTableViz9019D4275A2B4124B398FEE443B05F9F",
              "objects": {},
              "orderBy": [
                {
                  "Direction": 2,
                  "Expression": {
                    "Aggregation": {
                      "Expression": {
                        "Column": {
                          "Expression": {
                            "SourceRef": {
                              "Entity": "Armenia Import"
                            }
                          },
                          "Property": "TOTAL_ASSESS_USD"
                        }
                      },
                      "Function": 0
                    }
                  }
                }
              ]
            }
          },
          "9a3eeb39951dc5058ac0": {
            "filters": {
              "byExpr": [
                {
                  "name": "f3703c60f848073e19bd",
                  "type": "Advanced",
                  "expression": {
                    "Column": {
                      "Expression": {
                        "SourceRef": {
                          "Entity": "TOP 50 Importer"
                        }
                      },
                      "Property": "Value"
                    }
                  },
                  "howCreated": 0
                }
              ]
            },
            "singleVisual": {
              "visualType": "advancedSlicerVisual",
              "objects": {
                "merge": {
                  "general": [
                    {
                      "properties": {
                        "filter": {
                          "filter": {
                            "Version": 2,
                            "From": [
                              {
                                "Name": "t",
                                "Entity": "TOP 50 Importer",
                                "Type": 0
                              }
                            ],
                            "Where": [
                              {
                                "Condition": {
                                  "In": {
                                    "Expressions": [
                                      {
                                        "Column": {
                                          "Expression": {
                                            "SourceRef": {
                                              "Source": "t"
                                            }
                                          },
                                          "Property": "Value"
                                        }
                                      }
                                    ],
                                    "Values": [
                                      [
                                        {
                                          "Literal": {
                                            "Value": "20L"
                                          }
                                        }
                                      ]
                                    ]
                                  }
                                }
                              }
                            ]
                          }
                        }
                      }
                    }
                  ],
                  "selection": [
                    {
                      "properties": {
                        "strictSingleSelect": {
                          "expr": {
                            "Literal": {
                              "Value": "true"
                            }
                          }
                        }
                      }
                    }
                  ]
                }
              }
            }
          },
          "15cb0a632b96096e136d": {
            "filters": {
              "byExpr": [
                {
                  "name": "4aa96818b0cd8b7e2164",
                  "type": "Categorical",
                  "expression": {
                    "Column": {
                      "Expression": {
                        "SourceRef": {
                          "Entity": "Data"
                        }
                      },
                      "Property": "Data"
                    }
                  },
                  "howCreated": 0
                }
              ]
            },
            "singleVisual": {
              "visualType": "advancedSlicerVisual",
              "objects": {
                "merge": {
                  "general": [
                    {
                      "properties": {
                        "filter": {
                          "filter": {
                            "Version": 2,
                            "From": [
                              {
                                "Name": "d",
                                "Entity": "Data",
                                "Type": 0
                              }
                            ],
                            "Where": [
                              {
                                "Condition": {
                                  "In": {
                                    "Expressions": [
                                      {
                                        "Column": {
                                          "Expression": {
                                            "SourceRef": {
                                              "Source": "d"
                                            }
                                          },
                                          "Property": "Data Fields"
                                        }
                                      }
                                    ],
                                    "Values": [
                                      [
                                        {
                                          "Literal": {
                                            "Value": "'''All Measures''[Total Value]'"
                                          }
                                        }
                                      ]
                                    ]
                                  }
                                }
                              }
                            ]
                          }
                        }
                      }
                    }
                  ]
                }
              },
              "cachedFilterDisplayItems": [
                {
                  "id": {
                    "scopeId": {
                      "Comparison": {
                        "ComparisonKind": 0,
                        "Left": {
                          "Column": {
                            "Expression": {
                              "SourceRef": {
                                "Entity": "Data"
                              }
                            },
                            "Property": "Data Fields"
                          }
                        },
                        "Right": {
                          "Literal": {
                            "Value": "'''All Measures''[Total Value]'"
                          }
                        }
                      }
                    }
                  },
                  "displayName": "Value"
                }
              ]
            }
          },
          "5509a606bb3e58d22548": {
            "filters": {
              "byExpr": [
                {
                  "name": "0ac97e62b44bbf438138",
                  "type": "Advanced",
                  "filter": {
                    "Version": 2,
                    "From": [
                      {
                        "Name": "a",
                        "Entity": "All Measures",
                        "Type": 0
                      }
                    ],
                    "Where": [
                      {
                        "Condition": {
                          "Not": {
                            "Expression": {
                              "Comparison": {
                                "ComparisonKind": 0,
                                "Left": {
                                  "Measure": {
                                    "Expression": {
                                      "SourceRef": {
                                        "Source": "a"
                                      }
                                    },
                                    "Property": "Sum Total Value"
                                  }
                                },
                                "Right": {
                                  "Literal": {
                                    "Value": "null"
                                  }
                                }
                              }
                            }
                          }
                        }
                      }
                    ]
                  },
                  "expression": {
                    "Measure": {
                      "Expression": {
                        "SourceRef": {
                          "Entity": "All Measures"
                        }
                      },
                      "Property": "Sum Total Value"
                    }
                  },
                  "howCreated": 0
                },
                {
                  "name": "9c9e577390fec882480e",
                  "type": "Categorical",
                  "expression": {
                    "Column": {
                      "Expression": {
                        "SourceRef": {
                          "Entity": "Armenia Import"
                        }
                      },
                      "Property": "IMPORTER_NAME"
                    }
                  },
                  "howCreated": 0
                },
                {
                  "name": "f3eb97d79d6726abc2cd",
                  "type": "Categorical",
                  "expression": {
                    "Column": {
                      "Expression": {
                        "SourceRef": {
                          "Entity": "Armenia Import"
                        }
                      },
                      "Property": "SUPPLIER_NAME"
                    }
                  },
                  "howCreated": 0
                }
              ]
            },
            "singleVisual": {
              "visualType": "testTooltip4696B540F3494FE5BA002362825DDE7D",
              "objects": {},
              "orderBy": [
                {
                  "Direction": 2,
                  "Expression": {
                    "Measure": {
                      "Expression": {
                        "SourceRef": {
                          "Entity": "All Measures"
                        }
                      },
                      "Property": "Sum Total Value"
                    }
                  }
                }
              ]
            }
          },
          "75b3b024908a03e5182d": {
            "filters": {
              "byExpr": [
                {
                  "name": "a62ae257cfa8fe6d0b6a",
                  "type": "Categorical",
                  "expression": {
                    "Column": {
                      "Expression": {
                        "SourceRef": {
                          "Entity": "Armenia Import"
                        }
                      },
                      "Property": "SUPPLIER_NAME"
                    }
                  },
                  "howCreated": 0
                }
              ]
            },
            "singleVisual": {
              "visualType": "slicer",
              "objects": {
                "merge": {
                  "data": [
                    {
                      "properties": {
                        "mode": {
                          "expr": {
                            "Literal": {
                              "Value": "'Dropdown'"
                            }
                          }
                        }
                      }
                    }
                  ],
                  "selection": [
                    {
                      "properties": {
                        "strictSingleSelect": {
                          "expr": {
                            "Literal": {
                              "Value": "false"
                            }
                          }
                        }
                      }
                    }
                  ]
                }
              },
              "activeProjections": {
                "Values": [
                  {
                    "Column": {
                      "Expression": {
                        "SourceRef": {
                          "Entity": "Armenia Import"
                        }
                      },
                      "Property": "SUPPLIER_NAME"
                    }
                  }
                ]
              }
            }
          },
          "ddf1bc4b505b7e303d35": {
            "filters": {
              "byExpr": [
                {
                  "name": "902b7fa013cf8a7520ea",
                  "type": "Categorical",
                  "expression": {
                    "Column": {
                      "Expression": {
                        "SourceRef": {
                          "Entity": "Armenia Import"
                        }
                      },
                      "Property": "ORIGIN_COUNTRY"
                    }
                  },
                  "howCreated": 0
                }
              ]
            },
            "singleVisual": {
              "visualType": "slicer",
              "objects": {
                "merge": {
                  "data": [
                    {
                      "properties": {
                        "mode": {
                          "expr": {
                            "Literal": {
                              "Value": "'Dropdown'"
                            }
                          }
                        }
                      }
                    }
                  ],
                  "selection": [
                    {
                      "properties": {
                        "strictSingleSelect": {
                          "expr": {
                            "Literal": {
                              "Value": "false"
                            }
                          }
                        }
                      }
                    }
                  ]
                }
              },
              "activeProjections": {
                "Values": [
                  {
                    "Column": {
                      "Expression": {
                        "SourceRef": {
                          "Entity": "Armenia Import"
                        }
                      },
                      "Property": "ORIGIN_COUNTRY"
                    }
                  }
                ]
              }
            }
          },
          "1189bdc690167ac55429": {
            "filters": {
              "byExpr": [
                {
                  "name": "4cdbaa06bc774af3bf49",
                  "type": "Advanced",
                  "expression": {
                    "Aggregation": {
                      "Expression": {
                        "Column": {
                          "Expression": {
                            "SourceRef": {
                              "Entity": "Armenia Import"
                            }
                          },
                          "Property": "TOTAL_ASSESS_USD"
                        }
                      },
                      "Function": 0
                    }
                  },
                  "howCreated": 0
                },
                {
                  "name": "c2c3e0e0f93ed0347563",
                  "type": "Categorical",
                  "expression": {
                    "Column": {
                      "Expression": {
                        "SourceRef": {
                          "Entity": "Armenia Import"
                        }
                      },
                      "Property": "IMPORTER_NAME"
                    }
                  },
                  "howCreated": 0
                },
                {
                  "name": "95191539b806b2c2efe1",
                  "type": "Categorical",
                  "expression": {
                    "Column": {
                      "Expression": {
                        "SourceRef": {
                          "Entity": "Armenia Import"
                        }
                      },
                      "Property": "SUPPLIER_NAME"
                    }
                  },
                  "howCreated": 0
                },
                {
                  "name": "6d6d1e0b3f35672848dc",
                  "type": "Categorical",
                  "expression": {
                    "Column": {
                      "Expression": {
                        "SourceRef": {
                          "Entity": "Armenia Import"
                        }
                      },
                      "Property": "HS_CODE"
                    }
                  },
                  "howCreated": 0
                },
                {
                  "name": "49313a200b0dd2f0477c",
                  "type": "Categorical",
                  "expression": {
                    "Column": {
                      "Expression": {
                        "SourceRef": {
                          "Entity": "Armenia Import"
                        }
                      },
                      "Property": "INDIAN_PORT"
                    }
                  },
                  "howCreated": 0
                },
                {
                  "name": "ca52ebc057bfca6bf49d",
                  "type": "Categorical",
                  "expression": {
                    "Column": {
                      "Expression": {
                        "SourceRef": {
                          "Entity": "Armenia Import"
                        }
                      },
                      "Property": "ORIGIN_COUNTRY"
                    }
                  },
                  "howCreated": 0
                },
                {
                  "name": "ea410a5465394a666b36",
                  "type": "Categorical",
                  "expression": {
                    "Column": {
                      "Expression": {
                        "SourceRef": {
                          "Entity": "Armenia Import"
                        }
                      },
                      "Property": "PORT_OF_SHIPMENT"
                    }
                  },
                  "howCreated": 0
                }
              ]
            },
            "singleVisual": {
              "visualType": "decompositionTreeVisual",
              "objects": {},
              "orderBy": [
                {
                  "Direction": 2,
                  "Expression": {
                    "Aggregation": {
                      "Expression": {
                        "Column": {
                          "Expression": {
                            "SourceRef": {
                              "Entity": "IndiaImport (2)"
                            }
                          },
                          "Property": "TOTAL_ASSESS_USD"
                        }
                      },
                      "Function": 0
                    }
                  }
                }
              ],
              "activeProjections": {
                "ExplainBy": [
                  {
                    "Column": {
                      "Expression": {
                        "SourceRef": {
                          "Entity": "Armenia Import"
                        }
                      },
                      "Property": "IMPORTER_NAME"
                    }
                  },
                  {
                    "Column": {
                      "Expression": {
                        "SourceRef": {
                          "Entity": "Armenia Import"
                        }
                      },
                      "Property": "SUPPLIER_NAME"
                    }
                  },
                  {
                    "Column": {
                      "Expression": {
                        "SourceRef": {
                          "Entity": "Armenia Import"
                        }
                      },
                      "Property": "HS_CODE"
                    }
                  },
                  {
                    "Column": {
                      "Expression": {
                        "SourceRef": {
                          "Entity": "Armenia Import"
                        }
                      },
                      "Property": "INDIAN_PORT"
                    }
                  },
                  {
                    "Column": {
                      "Expression": {
                        "SourceRef": {
                          "Entity": "Armenia Import"
                        }
                      },
                      "Property": "ORIGIN_COUNTRY"
                    }
                  },
                  {
                    "Column": {
                      "Expression": {
                        "SourceRef": {
                          "Entity": "Armenia Import"
                        }
                      },
                      "Property": "PORT_OF_SHIPMENT"
                    }
                  }
                ]
              },
              "expansionStates": [
                {
                  "roles": [
                    "ExplainBy"
                  ],
                  "levels": [
                    {
                      "queryRefs": [
                        "IndiaImport.IMPORTER_NAME"
                      ],
                      "isCollapsed": true,
                      "identityKeys": [
                        {
                          "Column": {
                            "Expression": {
                              "SourceRef": {
                                "Entity": "IndiaImport"
                              }
                            },
                            "Property": "IMPORTER_NAME"
                          }
                        }
                      ],
                      "isPinned": true
                    },
                    {
                      "queryRefs": [
                        "IndiaImport.SUPPLIER_NAME"
                      ],
                      "isCollapsed": true,
                      "identityKeys": [
                        {
                          "Column": {
                            "Expression": {
                              "SourceRef": {
                                "Entity": "IndiaImport"
                              }
                            },
                            "Property": "SUPPLIER_NAME"
                          }
                        }
                      ],
                      "isPinned": true
                    },
                    {
                      "queryRefs": [
                        "IndiaImport.HS_CODE"
                      ],
                      "isCollapsed": true,
                      "identityKeys": [
                        {
                          "Column": {
                            "Expression": {
                              "SourceRef": {
                                "Entity": "IndiaImport"
                              }
                            },
                            "Property": "HS_CODE"
                          }
                        }
                      ],
                      "isPinned": true
                    },
                    {
                      "queryRefs": [
                        "IndiaImport.INDIAN_PORT"
                      ],
                      "isCollapsed": true,
                      "identityKeys": [
                        {
                          "Column": {
                            "Expression": {
                              "SourceRef": {
                                "Entity": "IndiaImport"
                              }
                            },
                            "Property": "INDIAN_PORT"
                          }
                        }
                      ],
                      "isPinned": true
                    },
                    {
                      "queryRefs": [
                        "IndiaImport.ORIGIN_COUNTRY"
                      ],
                      "isCollapsed": true,
                      "identityKeys": [
                        {
                          "Column": {
                            "Expression": {
                              "SourceRef": {
                                "Entity": "IndiaImport"
                              }
                            },
                            "Property": "ORIGIN_COUNTRY"
                          }
                        }
                      ],
                      "isPinned": true
                    },
                    {
                      "queryRefs": [
                        "IndiaImport.PORT_OF_SHIPMENT"
                      ],
                      "isCollapsed": true,
                      "identityKeys": [
                        {
                          "Column": {
                            "Expression": {
                              "SourceRef": {
                                "Entity": "IndiaImport"
                              }
                            },
                            "Property": "PORT_OF_SHIPMENT"
                          }
                        }
                      ],
                      "isPinned": true
                    }
                  ],
                  "root": {
                    "identityValues": null,
                    "children": [
                      {
                        "identityValues": [
                          {
                            "Literal": {
                              "Value": "'AAA TRADING COMPANY'"
                            }
                          }
                        ],
                        "isToggled": true,
                        "children": [
                          {
                            "identityValues": [
                              {
                                "Literal": {
                                  "Value": "'ALI JAN S O HABIBULLAH'"
                                }
                              }
                            ],
                            "isToggled": true,
                            "children": [
                              {
                                "identityValues": [
                                  {
                                    "Literal": {
                                      "Value": "'12119049'"
                                    }
                                  }
                                ],
                                "isToggled": true,
                                "children": [
                                  {
                                    "identityValues": [
                                      {
                                        "Literal": {
                                          "Value": "'ATTARI ROAD'"
                                        }
                                      }
                                    ],
                                    "isToggled": true,
                                    "children": [
                                      {
                                        "identityValues": [
                                          {
                                            "Literal": {
                                              "Value": "'AFGHANISTAN'"
                                            }
                                          }
                                        ],
                                        "isToggled": true
                                      }
                                    ]
                                  }
                                ]
                              }
                            ]
                          }
                        ]
                      }
                    ]
                  }
                }
              ]
            }
          },
          "ea15cfa306a59c08beea": {
            "filters": {
              "byExpr": [
                {
                  "name": "Filter27ac6fbd3b507ee9b307",
                  "type": "Advanced",
                  "filter": {
                    "Version": 2,
                    "From": [
                      {
                        "Name": "a",
                        "Entity": "All Measures",
                        "Type": 0
                      }
                    ],
                    "Where": [
                      {
                        "Condition": {
                          "Not": {
                            "Expression": {
                              "Comparison": {
                                "ComparisonKind": 0,
                                "Left": {
                                  "Measure": {
                                    "Expression": {
                                      "SourceRef": {
                                        "Source": "a"
                                      }
                                    },
                                    "Property": "Hide Visual"
                                  }
                                },
                                "Right": {
                                  "Literal": {
                                    "Value": "null"
                                  }
                                }
                              }
                            }
                          }
                        }
                      }
                    ]
                  },
                  "expression": {
                    "Measure": {
                      "Expression": {
                        "SourceRef": {
                          "Entity": "All Measures"
                        }
                      },
                      "Property": "Hide Visual"
                    }
                  },
                  "howCreated": 1
                },
                {
                  "name": "d0ee083bbfddd98e464a",
                  "type": "Categorical",
                  "expression": {
                    "Column": {
                      "Expression": {
                        "SourceRef": {
                          "Entity": "Armenia Import"
                        }
                      },
                      "Property": "IMPORTER_NAME"
                    }
                  },
                  "howCreated": 0
                },
                {
                  "name": "cd0edff02d26483734dc",
                  "type": "Advanced",
                  "expression": {
                    "Aggregation": {
                      "Expression": {
                        "Column": {
                          "Expression": {
                            "SourceRef": {
                              "Entity": "Armenia Import"
                            }
                          },
                          "Property": "TOTAL_ASSESS_USD"
                        }
                      },
                      "Function": 0
                    }
                  },
                  "howCreated": 0
                },
                {
                  "name": "b1c8a8afcffe78d72016",
                  "type": "Categorical",
                  "expression": {
                    "Column": {
                      "Expression": {
                        "SourceRef": {
                          "Entity": "Armenia Import"
                        }
                      },
                      "Property": "HS_CODE"
                    }
                  },
                  "howCreated": 0
                }
              ]
            },
            "singleVisual": {
              "visualType": "barChart",
              "objects": {},
              "orderBy": [
                {
                  "Direction": 2,
                  "Expression": {
                    "Aggregation": {
                      "Expression": {
                        "Column": {
                          "Expression": {
                            "SourceRef": {
                              "Entity": "IndiaImport (2)"
                            }
                          },
                          "Property": "TOTAL_ASSESS_USD"
                        }
                      },
                      "Function": 0
                    }
                  }
                }
              ],
              "activeProjections": {
                "Category": [
                  {
                    "Column": {
                      "Expression": {
                        "SourceRef": {
                          "Entity": "Armenia Import"
                        }
                      },
                      "Property": "IMPORTER_NAME"
                    }
                  }
                ]
              }
            }
          },
          "e9948b6d47b75496c5ab": {
            "filters": {
              "byExpr": [
                {
                  "name": "90d5d67eb5d6e288507d",
                  "type": "Categorical",
                  "expression": {
                    "Column": {
                      "Expression": {
                        "SourceRef": {
                          "Entity": "Armenia Import"
                        }
                      },
                      "Property": "ORIGIN_COUNTRY"
                    }
                  },
                  "howCreated": 0
                },
                {
                  "name": "3688da5b15fb06cdaf4b",
                  "type": "Categorical",
                  "expression": {
                    "Column": {
                      "Expression": {
                        "SourceRef": {
                          "Entity": "Armenia Import"
                        }
                      },
                      "Property": "IMPORTER_NAME"
                    }
                  },
                  "howCreated": 0
                },
                {
                  "name": "1b07c861fa9858c08fed",
                  "type": "Advanced",
                  "expression": {
                    "Aggregation": {
                      "Expression": {
                        "Column": {
                          "Expression": {
                            "SourceRef": {
                              "Entity": "Armenia Import"
                            }
                          },
                          "Property": "TOTAL_ASSESS_USD"
                        }
                      },
                      "Function": 0
                    }
                  },
                  "howCreated": 0
                },
                {
                  "name": "73b024ba5ae55785c9ea",
                  "type": "Advanced",
                  "expression": {
                    "Aggregation": {
                      "Expression": {
                        "Column": {
                          "Expression": {
                            "SourceRef": {
                              "Entity": "Armenia Import"
                            }
                          },
                          "Property": "STD_QUANTITY"
                        }
                      },
                      "Function": 0
                    }
                  },
                  "howCreated": 0
                }
              ]
            },
            "singleVisual": {
              "visualType": "clusteredColumnChart",
              "objects": {},
              "orderBy": [
                {
                  "Direction": 1,
                  "Expression": {
                    "Column": {
                      "Expression": {
                        "SourceRef": {
                          "Entity": "IndiaImport (2)"
                        }
                      },
                      "Property": "ORIGIN_COUNTRY"
                    }
                  }
                },
                {
                  "Direction": 1,
                  "Expression": {
                    "Column": {
                      "Expression": {
                        "SourceRef": {
                          "Entity": "IndiaImport (2)"
                        }
                      },
                      "Property": "IMPORTER_NAME"
                    }
                  }
                }
              ],
              "activeProjections": {
                "Category": [
                  {
                    "Column": {
                      "Expression": {
                        "SourceRef": {
                          "Entity": "Armenia Import"
                        }
                      },
                      "Property": "ORIGIN_COUNTRY"
                    }
                  }
                ]
              }
            }
          },
          "db23e8aae56619a10581": {
            "filters": {
              "byExpr": [
                {
                  "name": "3664250e034d567e3d42",
                  "type": "Categorical",
                  "expression": {
                    "Column": {
                      "Expression": {
                        "SourceRef": {
                          "Entity": "Armenia Import"
                        }
                      },
                      "Property": "INDIAN_PORT"
                    }
                  },
                  "howCreated": 0
                },
                {
                  "name": "cc2d2e7f80ddbe24f117",
                  "type": "Categorical",
                  "expression": {
                    "Column": {
                      "Expression": {
                        "SourceRef": {
                          "Entity": "Armenia Import"
                        }
                      },
                      "Property": "IMPORTER_NAME"
                    }
                  },
                  "howCreated": 0
                },
                {
                  "name": "67693780b8680035408a",
                  "type": "Advanced",
                  "expression": {
                    "Aggregation": {
                      "Expression": {
                        "Column": {
                          "Expression": {
                            "SourceRef": {
                              "Entity": "Armenia Import"
                            }
                          },
                          "Property": "TOTAL_ASSESS_USD"
                        }
                      },
                      "Function": 0
                    }
                  },
                  "howCreated": 0
                },
                {
                  "name": "cd7b34289271a8751041",
                  "type": "Advanced",
                  "expression": {
                    "Aggregation": {
                      "Expression": {
                        "Column": {
                          "Expression": {
                            "SourceRef": {
                              "Entity": "Armenia Import"
                            }
                          },
                          "Property": "STD_QUANTITY"
                        }
                      },
                      "Function": 0
                    }
                  },
                  "howCreated": 0
                }
              ]
            },
            "singleVisual": {
              "visualType": "ribbonChart",
              "objects": {},
              "orderBy": [
                {
                  "Direction": 1,
                  "Expression": {
                    "Column": {
                      "Expression": {
                        "SourceRef": {
                          "Entity": "IndiaImport (2)"
                        }
                      },
                      "Property": "INDIAN_PORT"
                    }
                  }
                },
                {
                  "Direction": 1,
                  "Expression": {
                    "Column": {
                      "Expression": {
                        "SourceRef": {
                          "Entity": "IndiaImport (2)"
                        }
                      },
                      "Property": "IMPORTER_NAME"
                    }
                  }
                }
              ],
              "activeProjections": {
                "Category": [
                  {
                    "Column": {
                      "Expression": {
                        "SourceRef": {
                          "Entity": "Armenia Import"
                        }
                      },
                      "Property": "INDIAN_PORT"
                    }
                  }
                ]
              }
            }
          },
          "d9ebf75f08e95861b504": {
            "singleVisual": {
              "visualType": "shape",
              "objects": {}
            }
          },
          "a4d8de91eaa5071e56dc": {
            "singleVisual": {
              "visualType": "shape",
              "objects": {}
            }
          },
          "0b9c6502ba33e2620e55": {
            "singleVisual": {
              "visualType": "shape",
              "objects": {}
            }
          },
          "abc95e1490e50c28013e": {
            "singleVisual": {
              "visualType": "actionButton",
              "objects": {}
            }
          },
          "a3d006ae5d6a37f4c13a": {
            "singleVisual": {
              "visualType": "image",
              "objects": {}
            }
          },
          "60a67033eccf26cf488a": {
            "singleVisual": {
              "visualType": "textbox",
              "objects": {}
            }
          },
          "5d19a3df1f0d4288f2f1": {
            "singleVisual": {
              "visualType": "textbox",
              "objects": {}
            }
          },
          "79c14fe239db0f6a123d": {
            "singleVisual": {
              "visualType": "textbox",
              "objects": {}
            }
          },
          "e54b7fc5d6fbecaf5cae": {
            "singleVisual": {
              "visualType": "textbox",
              "objects": {}
            }
          },
          "198276d60ec8df83cd29": {
            "singleVisual": {
              "visualType": "image",
              "objects": {}
            }
          },
          "1a81a454662b6fbfb4d3": {
            "singleVisual": {
              "visualType": "textbox",
              "objects": {}
            }
          },
          "5b9dfa5d1c606e28139d": {
            "singleVisual": {
              "visualType": "shape",
              "objects": {}
            }
          },
          "bd7cb9c17fa762897650": {
            "singleVisual": {
              "visualType": "shape",
              "objects": {}
            }
          },
          "16d06df1f3f71d538d72": {
            "singleVisual": {
              "visualType": "shape",
              "objects": {}
            }
          },
          "1ad87d8b12d870faa391": {
            "singleVisual": {
              "visualType": "shape",
              "objects": {}
            }
          },
          "411dec4dc451f9c0d7a2": {
            "singleVisual": {
              "visualType": "shape",
              "objects": {}
            }
          },
          "12ba177e5632010875c9": {
            "singleVisual": {
              "visualType": "actionButton",
              "objects": {}
            }
          },
          "6b9de63f0e440fe98b75": {
            "filters": {
              "byExpr": [
                {
                  "name": "Filter3eca18fd303a30048da3",
                  "type": "Advanced",
                  "filter": {
                    "Version": 2,
                    "From": [
                      {
                        "Name": "t",
                        "Entity": "TOP 50 Importer",
                        "Type": 0
                      }
                    ],
                    "Where": [
                      {
                        "Condition": {
                          "Comparison": {
                            "ComparisonKind": 0,
                            "Left": {
                              "Measure": {
                                "Expression": {
                                  "SourceRef": {
                                    "Source": "t"
                                  }
                                },
                                "Property": "TOP50 Importer Rank"
                              }
                            },
                            "Right": {
                              "Literal": {
                                "Value": "1L"
                              }
                            }
                          }
                        }
                      }
                    ]
                  },
                  "expression": {
                    "Measure": {
                      "Expression": {
                        "SourceRef": {
                          "Entity": "TOP 50 Importer"
                        }
                      },
                      "Property": "TOP50 Importer Rank"
                    }
                  },
                  "howCreated": 1
                },
                {
                  "name": "04506ecff0d9fa9d3a8a",
                  "type": "Categorical",
                  "expression": {
                    "Column": {
                      "Expression": {
                        "SourceRef": {
                          "Entity": "Armenia Import"
                        }
                      },
                      "Property": "IMPORTER_NAME"
                    }
                  },
                  "howCreated": 0
                },
                {
                  "name": "20865a14e7b6f4369c2f",
                  "type": "Advanced",
                  "expression": {
                    "Measure": {
                      "Expression": {
                        "SourceRef": {
                          "Entity": "All Measures"
                        }
                      },
                      "Property": "Total Value"
                    }
                  },
                  "howCreated": 0
                }
              ]
            },
            "singleVisual": {
              "visualType": "clusteredBarChart",
              "objects": {},
              "orderBy": [
                {
                  "Direction": 2,
                  "Expression": {
                    "Measure": {
                      "Expression": {
                        "SourceRef": {
                          "Entity": "All Measures"
                        }
                      },
                      "Property": "Total Value"
                    }
                  }
                }
              ],
              "activeProjections": {
                "Category": [
                  {
                    "Column": {
                      "Expression": {
                        "SourceRef": {
                          "Entity": "Armenia Import"
                        }
                      },
                      "Property": "IMPORTER_NAME"
                    }
                  }
                ]
              },
              "projections": {
                "Y": [
                  {
                    "Measure": {
                      "Expression": {
                        "SourceRef": {
                          "Entity": "All Measures"
                        }
                      },
                      "Property": "Total Value"
                    }
                  }
                ],
                "Category": [
                  {
                    "Literal": {
                      "Value": "null"
                    }
                  }
                ]
              },
              "parameters": {
                "Series": [
                  {
                    "expr": {
                      "Column": {
                        "Expression": {
                          "SourceRef": {
                            "Entity": "Data"
                          }
                        },
                        "Property": "Data"
                      }
                    },
                    "index": 0,
                    "length": 0
                  }
                ],
                "Y": [
                  {
                    "expr": {
                      "Column": {
                        "Expression": {
                          "SourceRef": {
                            "Entity": "Data"
                          }
                        },
                        "Property": "Data Fields"
                      }
                    },
                    "index": 0,
                    "length": 1
                  }
                ]
              }
            }
          },
          "516f3735e063d5004933": {
            "singleVisual": {
              "visualType": "shape",
              "objects": {}
            }
          },
          "0e33f8b9620097b20791": {
            "singleVisual": {
              "visualType": "shape",
              "objects": {}
            }
          },
          "0f8c61cfc9bd6a389b28": {
            "filters": {
              "byExpr": [
                {
                  "name": "c267196118b7ce22f216",
                  "type": "Categorical",
                  "expression": {
                    "Column": {
                      "Expression": {
                        "SourceRef": {
                          "Entity": "Armenia Import"
                        }
                      },
                      "Property": "IMPORTER_NAME"
                    }
                  },
                  "howCreated": 0
                }
              ]
            },
            "singleVisual": {
              "visualType": "slicer",
              "objects": {
                "merge": {
                  "data": [
                    {
                      "properties": {
                        "mode": {
                          "expr": {
                            "Literal": {
                              "Value": "'Basic'"
                            }
                          }
                        }
                      }
                    }
                  ]
                }
              },
              "activeProjections": {
                "Values": [
                  {
                    "Column": {
                      "Expression": {
                        "SourceRef": {
                          "Entity": "Armenia Import"
                        }
                      },
                      "Property": "IMPORTER_NAME"
                    }
                  }
                ]
              }
            }
          }
        },
        "visualContainerGroups": {
          "669291ff677ce7faf6ec": {
            "isHidden": true
          }
        }
      }
    },
    "objects": {
      "merge": {
        "outspacePane": [
          {
            "properties": {
              "expanded": {
                "expr": {
                  "Literal": {
                    "Value": "false"
                  }
                }
              }
            }
          }
        ]
      }
    }
  }
}