{
  "$schema": "https://developer.microsoft.com/json-schemas/fabric/item/report/definition/visualContainer/2.1.0/schema.json",
  "name": "a0e074cfeb8da6db449b",
  "position": {
    "x": 0,
    "y": 24.765748654637605,
    "z": 1500,
    "height": 66.666666666666671,
    "width": 230,
    "tabOrder": 34014
  },
  "visual": {
    "visualType": "multiCardVisual46301BE6FD68470785DDC302DA47C4C9",
    "query": {
      "queryState": {
        "colorMeasure": {
          "projections": [
            {
              "field": {
                "Measure": {
                  "Expression": {
                    "SourceRef": {
                      "Entity": "ALL Measures"
                    }
                  },
                  "Property": "Arrow FTU Color"
                }
              },
              "queryRef": "ALL Measures.Arrow FTU Color",
              "nativeQueryRef": "Arrow FTU Color"
            }
          ]
        },
        "bigNumber": {
          "projections": [
            {
              "field": {
                "Aggregation": {
                  "Expression": {
                    "Column": {
                      "Expression": {
                        "SourceRef": {
                          "Entity": "Food-BigNo-Today"
                        }
                      },
                      "Property": "TransactingUserCount"
                    }
                  },
                  "Function": 0
                }
              },
              "queryRef": "Sum(Food-BigNo-Today.TransactingUserCount)",
              "nativeQueryRef": "Sum of TransactingUserCount"
            }
          ]
        },
        "arrow": {
          "projections": [
            {
              "field": {
                "Measure": {
                  "Expression": {
                    "SourceRef": {
                      "Entity": "ALL Measures"
                    }
                  },
                  "Property": "Arrow WOW% FTU"
                }
              },
              "queryRef": "ALL Measures.Arrow WOW% FTU",
              "nativeQueryRef": "Arrow WOW% FTU"
            }
          ]
        },
        "wow": {
          "projections": [
            {
              "field": {
                "Measure": {
                  "Expression": {
                    "SourceRef": {
                      "Entity": "ALL Measures"
                    }
                  },
                  "Property": "Transacting Users % WOW-Today"
                }
              },
              "queryRef": "ALL Measures.Transacting Users % WOW-Today",
              "nativeQueryRef": "Transacting Users % WOW-Today"
            }
          ]
        }
      },
      "sortDefinition": {
        "sort": [
          {
            "field": {
              "Aggregation": {
                "Expression": {
                  "Column": {
                    "Expression": {
                      "SourceRef": {
                        "Entity": "Food-BigNo-Today"
                      }
                    },
                    "Property": "TransactingUserCount"
                  }
                },
                "Function": 0
              }
            },
            "direction": "Descending"
          }
        ],
        "isDefaultSort": true
      }
    },
    "visualContainerObjects": {
      "title": [
        {
          "properties": {
            "show": {
              "expr": {
                "Literal": {
                  "Value": "false"
                }
              }
            }
          }
        }
      ],
      "background": [
        {
          "properties": {
            "show": {
              "expr": {
                "Literal": {
                  "Value": "false"
                }
              }
            }
          }
        }
      ]
    },
    "drillFilterOtherVisuals": true
  },
  "parentGroupName": "ce1426bd78eb099b9727"
}